<?xml version="1.0" encoding="UTF-8"?>
<config xmlns="http://www.knime.org/2008/09/XMLConfig" xmlns:xsi="http://www.w3.org/2001/XMLSchema-instance" xsi:schemaLocation="http://www.knime.org/2008/09/XMLConfig http://www.knime.org/XMLConfig_2008_09.xsd" key="spec.xml">
    <entry key="spec_name" type="xstring" value="default"/>
    <entry key="number_columns" type="xint" value="11"/>
    <config key="column_spec_0">
        <entry key="column_name" type="xstring" value="Mois"/>
        <config key="element_names">
            <entry key="array-size" type="xint" value="0"/>
        </config>
        <config key="column_type">
            <entry key="cell_class" type="xstring" value="org.knime.core.data.def.DoubleCell"/>
        </config>
        <config key="column_domain">
            <config key="lower_bound">
                <entry key="datacell" type="xstring" value="org.knime.core.data.def.DoubleCell"/>
                <config key="org.knime.core.data.def.DoubleCell">
                    <entry key="DoubleCell" type="xdouble" value="4.078571428571428"/>
                </config>
            </config>
            <config key="upper_bound">
                <entry key="datacell" type="xstring" value="org.knime.core.data.def.DoubleCell"/>
                <config key="org.knime.core.data.def.DoubleCell">
                    <entry key="DoubleCell" type="xdouble" value="7.583333333333333"/>
                </config>
            </config>
        </config>
        <config key="column_properties"/>
        <config key="meta_data"/>
    </config>
    <config key="column_spec_1">
        <entry key="column_name" type="xstring" value="Saison"/>
        <config key="element_names">
            <entry key="array-size" type="xint" value="0"/>
        </config>
        <config key="column_type">
            <entry key="cell_class" type="xstring" value="org.knime.core.data.def.DoubleCell"/>
        </config>
        <config key="column_domain">
            <config key="lower_bound">
                <entry key="datacell" type="xstring" value="org.knime.core.data.def.DoubleCell"/>
                <config key="org.knime.core.data.def.DoubleCell">
                    <entry key="DoubleCell" type="xdouble" value="1.6928571428571428"/>
                </config>
            </config>
            <config key="upper_bound">
                <entry key="datacell" type="xstring" value="org.knime.core.data.def.DoubleCell"/>
                <config key="org.knime.core.data.def.DoubleCell">
                    <entry key="DoubleCell" type="xdouble" value="2.802197802197802"/>
                </config>
            </config>
        </config>
        <config key="column_properties"/>
        <config key="meta_data"/>
    </config>
    <config key="column_spec_2">
        <entry key="column_name" type="xstring" value="JourFerie"/>
        <config key="element_names">
            <entry key="array-size" type="xint" value="0"/>
        </config>
        <config key="column_type">
            <entry key="cell_class" type="xstring" value="org.knime.core.data.def.DoubleCell"/>
        </config>
        <config key="column_domain">
            <config key="lower_bound">
                <entry key="datacell" type="xstring" value="org.knime.core.data.def.DoubleCell"/>
                <config key="org.knime.core.data.def.DoubleCell">
                    <entry key="DoubleCell" type="xdouble" value="0.0"/>
                </config>
            </config>
            <config key="upper_bound">
                <entry key="datacell" type="xstring" value="org.knime.core.data.def.DoubleCell"/>
                <config key="org.knime.core.data.def.DoubleCell">
                    <entry key="DoubleCell" type="xdouble" value="0.04285714285714286"/>
                </config>
            </config>
        </config>
        <config key="column_properties"/>
        <config key="meta_data"/>
    </config>
    <config key="column_spec_3">
        <entry key="column_name" type="xstring" value="JourSemaine"/>
        <config key="element_names">
            <entry key="array-size" type="xint" value="0"/>
        </config>
        <config key="column_type">
            <entry key="cell_class" type="xstring" value="org.knime.core.data.def.DoubleCell"/>
        </config>
        <config key="column_domain">
            <config key="lower_bound">
                <entry key="datacell" type="xstring" value="org.knime.core.data.def.DoubleCell"/>
                <config key="org.knime.core.data.def.DoubleCell">
                    <entry key="DoubleCell" type="xdouble" value="2.8626373626373627"/>
                </config>
            </config>
            <config key="upper_bound">
                <entry key="datacell" type="xstring" value="org.knime.core.data.def.DoubleCell"/>
                <config key="org.knime.core.data.def.DoubleCell">
                    <entry key="DoubleCell" type="xdouble" value="3.1597222222222223"/>
                </config>
            </config>
        </config>
        <config key="column_properties"/>
        <config key="meta_data"/>
    </config>
    <config key="column_spec_4">
        <entry key="column_name" type="xstring" value="JourTravail"/>
        <config key="element_names">
            <entry key="array-size" type="xint" value="0"/>
        </config>
        <config key="column_type">
            <entry key="cell_class" type="xstring" value="org.knime.core.data.def.DoubleCell"/>
        </config>
        <config key="column_domain">
            <config key="lower_bound">
                <entry key="datacell" type="xstring" value="org.knime.core.data.def.DoubleCell"/>
                <config key="org.knime.core.data.def.DoubleCell">
                    <entry key="DoubleCell" type="xdouble" value="0.6142857142857143"/>
                </config>
            </config>
            <config key="upper_bound">
                <entry key="datacell" type="xstring" value="org.knime.core.data.def.DoubleCell"/>
                <config key="org.knime.core.data.def.DoubleCell">
                    <entry key="DoubleCell" type="xdouble" value="0.7197802197802198"/>
                </config>
            </config>
        </config>
        <config key="column_properties"/>
        <config key="meta_data"/>
    </config>
    <config key="column_spec_5">
        <entry key="column_name" type="xstring" value="Meteo"/>
        <config key="element_names">
            <entry key="array-size" type="xint" value="0"/>
        </config>
        <config key="column_type">
            <entry key="cell_class" type="xstring" value="org.knime.core.data.def.DoubleCell"/>
        </config>
        <config key="column_domain">
            <config key="lower_bound">
                <entry key="datacell" type="xstring" value="org.knime.core.data.def.DoubleCell"/>
                <config key="org.knime.core.data.def.DoubleCell">
                    <entry key="DoubleCell" type="xdouble" value="1.0212765957446808"/>
                </config>
            </config>
            <config key="upper_bound">
                <entry key="datacell" type="xstring" value="org.knime.core.data.def.DoubleCell"/>
                <config key="org.knime.core.data.def.DoubleCell">
                    <entry key="DoubleCell" type="xdouble" value="2.0725806451612905"/>
                </config>
            </config>
        </config>
        <config key="column_properties"/>
        <config key="meta_data"/>
    </config>
    <config key="column_spec_6">
        <entry key="column_name" type="xstring" value="Temperature"/>
        <config key="element_names">
            <entry key="array-size" type="xint" value="0"/>
        </config>
        <config key="column_type">
            <entry key="cell_class" type="xstring" value="org.knime.core.data.def.DoubleCell"/>
        </config>
        <config key="column_domain">
            <config key="lower_bound">
                <entry key="datacell" type="xstring" value="org.knime.core.data.def.DoubleCell"/>
                <config key="org.knime.core.data.def.DoubleCell">
                    <entry key="DoubleCell" type="xdouble" value="12.678571428571429"/>
                </config>
            </config>
            <config key="upper_bound">
                <entry key="datacell" type="xstring" value="org.knime.core.data.def.DoubleCell"/>
                <config key="org.knime.core.data.def.DoubleCell">
                    <entry key="DoubleCell" type="xdouble" value="27.77304964539007"/>
                </config>
            </config>
        </config>
        <config key="column_properties"/>
        <config key="meta_data"/>
    </config>
    <config key="column_spec_7">
        <entry key="column_name" type="xstring" value="TemperatureRessentie"/>
        <config key="element_names">
            <entry key="array-size" type="xint" value="0"/>
        </config>
        <config key="column_type">
            <entry key="cell_class" type="xstring" value="org.knime.core.data.def.DoubleCell"/>
        </config>
        <config key="column_domain">
            <config key="lower_bound">
                <entry key="datacell" type="xstring" value="org.knime.core.data.def.DoubleCell"/>
                <config key="org.knime.core.data.def.DoubleCell">
                    <entry key="DoubleCell" type="xdouble" value="15.285714285714286"/>
                </config>
            </config>
            <config key="upper_bound">
                <entry key="datacell" type="xstring" value="org.knime.core.data.def.DoubleCell"/>
                <config key="org.knime.core.data.def.DoubleCell">
                    <entry key="DoubleCell" type="xdouble" value="31.70921985815603"/>
                </config>
            </config>
        </config>
        <config key="column_properties"/>
        <config key="meta_data"/>
    </config>
    <config key="column_spec_8">
        <entry key="column_name" type="xstring" value="Humidex"/>
        <config key="element_names">
            <entry key="array-size" type="xint" value="0"/>
        </config>
        <config key="column_type">
            <entry key="cell_class" type="xstring" value="org.knime.core.data.def.DoubleCell"/>
        </config>
        <config key="column_domain">
            <config key="lower_bound">
                <entry key="datacell" type="xstring" value="org.knime.core.data.def.DoubleCell"/>
                <config key="org.knime.core.data.def.DoubleCell">
                    <entry key="DoubleCell" type="xdouble" value="45.292857142857144"/>
                </config>
            </config>
            <config key="upper_bound">
                <entry key="datacell" type="xstring" value="org.knime.core.data.def.DoubleCell"/>
                <config key="org.knime.core.data.def.DoubleCell">
                    <entry key="DoubleCell" type="xdouble" value="83.54838709677419"/>
                </config>
            </config>
        </config>
        <config key="column_properties"/>
        <config key="meta_data"/>
    </config>
    <config key="column_spec_9">
        <entry key="column_name" type="xstring" value="VitesseVent"/>
        <config key="element_names">
            <entry key="array-size" type="xint" value="0"/>
        </config>
        <config key="column_type">
            <entry key="cell_class" type="xstring" value="org.knime.core.data.def.DoubleCell"/>
        </config>
        <config key="column_domain">
            <config key="lower_bound">
                <entry key="datacell" type="xstring" value="org.knime.core.data.def.DoubleCell"/>
                <config key="org.knime.core.data.def.DoubleCell">
                    <entry key="DoubleCell" type="xdouble" value="11.247252747252746"/>
                </config>
            </config>
            <config key="upper_bound">
                <entry key="datacell" type="xstring" value="org.knime.core.data.def.DoubleCell"/>
                <config key="org.knime.core.data.def.DoubleCell">
                    <entry key="DoubleCell" type="xdouble" value="16.192857142857143"/>
                </config>
            </config>
        </config>
        <config key="column_properties"/>
        <config key="meta_data"/>
    </config>
    <config key="column_spec_10">
        <entry key="column_name" type="xstring" value="HauteDemande"/>
        <config key="element_names">
            <entry key="array-size" type="xint" value="0"/>
        </config>
        <config key="column_type">
            <entry key="cell_class" type="xstring" value="org.knime.core.data.def.DoubleCell"/>
        </config>
        <config key="column_domain">
            <config key="lower_bound">
                <entry key="datacell" type="xstring" value="org.knime.core.data.def.DoubleCell"/>
                <config key="org.knime.core.data.def.DoubleCell">
                    <entry key="DoubleCell" type="xdouble" value="0.22580645161290322"/>
                </config>
            </config>
            <config key="upper_bound">
                <entry key="datacell" type="xstring" value="org.knime.core.data.def.DoubleCell"/>
                <config key="org.knime.core.data.def.DoubleCell">
                    <entry key="DoubleCell" type="xdouble" value="0.8297872340425532"/>
                </config>
            </config>
        </config>
        <config key="column_properties"/>
        <config key="meta_data"/>
    </config>
</config>
